pyIBA/IDF.py
pyIBA/__init__.py
pyIBA/auxiliar.py
pyIBA/main_idf.py
pyIBA/aux_files/MANUAL_100a.docx
pyIBA/aux_files/MANUAL_100a.pdf
pyIBA/aux_files/idf_style.xml
pyIBA/codes/IDF2NDF.py
pyIBA/codes/NDF.py
pyIBA/codes/__init__.py
pyIBA/codes/NDF_11_MS/IDF2NDF.exe
pyIBA/codes/NDF_11_MS/NDF.exe
pyIBA/codes/NDF_11_MS/NDF/windf/SCOEF03.dat
pyIBA/codes/NDF_11_MS/NDF/windf/SC_PRA74.fck
pyIBA/codes/NDF_11_MS/NDF/windf/SNUC03.dat
pyIBA/codes/NDF_11_MS/NDF/windf/SRModule.exe
pyIBA/codes/NDF_11_MS/NDF/windf/Scoef.95a
pyIBA/codes/NDF_11_MS/NDF/windf/Scoef.95b
pyIBA/codes/NDF_11_MS/NDF/windf/isotopes.dat
pyIBA/codes/NDF_11_MS/NDF/windf/license.ndf
pyIBA/codes/NDF_11_MS/NDF/windf/pscoef.dat
pyIBA/codes/NDF_11_MS/NDF/windf/rbssim.dat
pyIBA/codes/NDF_11_MS/NDF/windf/rbssimnew.dat
pyIBA/codes/NDF_11_MS/NDF/windf/sigmacalc_14Jan11.zip
pyIBA/codes/NDF_11_MS/NDF/windf/sr.in
pyIBA/codes/NDF_11_MS/NDF/windf/sr.out
pyIBA/codes/NDF_11_MS/NDF/windf/version
pyIBA/codes/NDF_11_MS/NDF/windf/xabs.abs
pyIBA/codes/NDF_11_MS/NDF/windf/xener.dat
pyIBA/codes/NDF_11_MS/NDF/windf/se/1H12Cp.se
pyIBA/codes/NDF_11_MS/NDF/windf/se/1H12Cq.se
pyIBA/codes/NDF_11_MS/NDF/windf/se/1H12Cr.se
pyIBA/codes/NDF_11_MS/NDF/windf/se/1H12Cs.se
pyIBA/codes/NDF_11_MS/NDF/windf/se/1H1Hp.se
pyIBA/codes/NDF_11_MS/NDF/windf/se/1H1Hq.se
pyIBA/codes/NDF_11_MS/NDF/windf/se/1H1Hr.se
pyIBA/codes/NDF_11_MS/NDF/windf/se/1H1Hs.se
pyIBA/codes/NDF_11_MS/NDF/windf/se/1H2Hp.se
pyIBA/codes/NDF_11_MS/NDF/windf/se/1H2Hq.se
pyIBA/codes/NDF_11_MS/NDF/windf/se/1H2Hr.se
pyIBA/codes/NDF_11_MS/NDF/windf/se/1H2Hs.se
pyIBA/codes/NDF_11_MS/NDF/windf/se/1HBep.se
pyIBA/codes/NDF_11_MS/NDF/windf/se/1HBeq.se
pyIBA/codes/NDF_11_MS/NDF/windf/se/1HBer.se
pyIBA/codes/NDF_11_MS/NDF/windf/se/1HBes.se
pyIBA/codes/NDF_11_MS/NDF/windf/se/1HCp.se
pyIBA/codes/NDF_11_MS/NDF/windf/se/1HCq.se
pyIBA/codes/NDF_11_MS/NDF/windf/se/1HCr.se
pyIBA/codes/NDF_11_MS/NDF/windf/se/1HCrp.se
pyIBA/codes/NDF_11_MS/NDF/windf/se/1HCrq.se
pyIBA/codes/NDF_11_MS/NDF/windf/se/1HCrr.se
pyIBA-1.0.dist-info/METADATA
pyIBA-1.0.dist-info/WHEEL
pyIBA-1.0.dist-info/top_level.txt
pyIBA-1.0.dist-info/RECORD
